vod/__init__.py
vod/vod.py
vod/can_bus/can_bus_api.py
vod/eval/__init__.py
vod/eval/common/__init__.py
vod/eval/common/config.py
vod/eval/common/data_classes.py
vod/eval/common/loaders.py
vod/eval/common/render.py
vod/eval/common/utils.py
vod/eval/detection/__init__.py
vod/eval/detection/algo.py
vod/eval/detection/config.py
vod/eval/detection/constants.py
vod/eval/detection/data_classes.py
vod/eval/detection/evaluate.py
vod/eval/detection/render.py
vod/eval/detection/utils.py
vod/eval/detection/tests/__init__.py
vod/eval/detection/tests/test_algo.py
vod/eval/detection/tests/test_data_classes.py
vod/eval/detection/tests/test_evaluate.py
vod/eval/detection/tests/test_loader.py
vod/eval/detection/tests/test_utils.py
vod/eval/lidarseg/__init__.py
vod/eval/lidarseg/evaluate.py
vod/eval/lidarseg/render.py
vod/eval/lidarseg/utils.py
vod/eval/lidarseg/validate_submission.py
vod/eval/lidarseg/tests/__init__.py
vod/eval/panoptic/__init__.py
vod/eval/panoptic/baselines.py
vod/eval/panoptic/evaluate.py
vod/eval/panoptic/get_panoptic_from_seg_det_or_track.py
vod/eval/panoptic/panoptic_seg_evaluator.py
vod/eval/panoptic/panoptic_track_evaluator.py
vod/eval/panoptic/utils.py
vod/eval/prediction/__init__.py
vod/eval/prediction/baseline_model_inference.py
vod/eval/prediction/compute_metrics.py
vod/eval/prediction/config.py
vod/eval/prediction/data_classes.py
vod/eval/prediction/metrics.py
vod/eval/prediction/splits.py
vod/eval/prediction/submission/__init__.py
vod/eval/prediction/submission/do_inference.py
vod/eval/prediction/tests/__init__.py
vod/eval/prediction/tests/test_dataclasses.py
vod/eval/prediction/tests/test_metrics.py
vod/eval/tracking/__init__.py
vod/eval/tracking/algo.py
vod/eval/tracking/constants.py
vod/eval/tracking/data_classes.py
vod/eval/tracking/evaluate.py
vod/eval/tracking/loaders.py
vod/eval/tracking/metrics.py
vod/eval/tracking/mot.py
vod/eval/tracking/render.py
vod/eval/tracking/utils.py
vod/eval/tracking/tests/__init__.py
vod_devkit-1.1.2.dist-info/LICENSE
vod_devkit-1.1.2.dist-info/METADATA
vod_devkit-1.1.2.dist-info/WHEEL
vod_devkit-1.1.2.dist-info/top_level.txt
vod_devkit-1.1.2.dist-info/RECORD
