Metadata-Version: 2.1
Name: vod-devkit
Version: 1.1.2
Summary: The official devkit of the View-of-Delft Prediction dataset.
Author-email: Hidde Boekema <h.j.boekema@tudelft.nl>
Project-URL: Homepage, https://intelligent-vehicles.org/datasets/view-of-delft/
Project-URL: Code, https://github.com/tudelft-iv/view-of-delft-prediction-devkit
Project-URL: Bug Tracker, https://github.com/tudelft-iv/view-of-delft-prediction-devkit/issues
Classifier: Development Status :: 3 - Alpha
Classifier: Intended Audience :: Developers
Classifier: Programming Language :: Python :: 3.8
Classifier: License :: OSI Approved :: Apache Software License
Requires-Python: >=3.8
License-File: LICENSE
Requires-Dist: cachetools
Requires-Dist: descartes
Requires-Dist: fire
Requires-Dist: matplotlib
Requires-Dist: numpy
Requires-Dist: opencv-python
Requires-Dist: Pillow
Requires-Dist: pyquaternion
Requires-Dist: scikit-learn
Requires-Dist: scipy
Requires-Dist: Shapely
Requires-Dist: tqdm
Requires-Dist: notebook
Provides-Extra: dev
Requires-Dist: black; extra == "dev"
Requires-Dist: isort; extra == "dev"
Requires-Dist: pytest; extra == "dev"
Requires-Dist: pytest-xdist; extra == "dev"
Requires-Dist: twine; extra == "dev"
Requires-Dist: build; extra == "dev"
Provides-Extra: prediction
Requires-Dist: torch>=1.3.1; extra == "prediction"
Requires-Dist: torchvision>=0.4.2; extra == "prediction"
Provides-Extra: tracking
Requires-Dist: motmetrics<=1.1.3; extra == "tracking"
Requires-Dist: pandas>=0.24; extra == "tracking"
